napari_webcam/__init__.py
napari_webcam/_dock_widget.py
napari_webcam/_function.py
napari_webcam/_tests/__init__.py
napari_webcam/_tests/test_dock_widget.py
napari_webcam/_tests/test_function.py
napari_webcam-0.1.19.dist-info/LICENSE
napari_webcam-0.1.19.dist-info/METADATA
napari_webcam-0.1.19.dist-info/WHEEL
napari_webcam-0.1.19.dist-info/top_level.txt
napari_webcam-0.1.19.dist-info/RECORD
