Metadata-Version: 2.1
Name: napari-webcam
Version: 0.1.19
Summary: Use your webcam from napari
Home-page: https://github.com/haesleinhuepf/napari-webcam
Author: Robert Haase
Author-email: robert.haase@tu-dresden.de
License: BSD-3
Platform: UNKNOWN
Classifier: Development Status :: 4 - Beta
Classifier: Intended Audience :: Developers
Classifier: Topic :: Software Development :: Testing
Classifier: Programming Language :: Python
Classifier: Programming Language :: Python :: 3
Classifier: Programming Language :: Python :: 3.7
Classifier: Programming Language :: Python :: 3.8
Classifier: Programming Language :: Python :: 3.9
Classifier: Operating System :: OS Independent
Classifier: License :: OSI Approved :: BSD License
Requires-Python: >=3.6
License-File: LICENSE
Requires-Dist: napari-plugin-engine (>=0.1.4)
Requires-Dist: numpy
Requires-Dist: opencv-python
Requires-Dist: napari
Requires-Dist: scikit-image
Requires-Dist: pyqt5
Requires-Dist: napari-tools-menu
